py_maker/.mypy_cache/.gitignore
py_maker/.mypy_cache/3.11/@plugins_snapshot.json
py_maker/.mypy_cache/3.11/__future__.data.json
py_maker/.mypy_cache/3.11/__future__.meta.json
py_maker/.mypy_cache/3.11/_ast.data.json
py_maker/.mypy_cache/3.11/_ast.meta.json
py_maker/.mypy_cache/3.11/_codecs.data.json
py_maker/.mypy_cache/3.11/_codecs.meta.json
py_maker/.mypy_cache/3.11/_collections_abc.data.json
py_maker/.mypy_cache/3.11/_collections_abc.meta.json
py_maker/.mypy_cache/3.11/_compression.data.json
py_maker/.mypy_cache/3.11/_compression.meta.json
py_maker/.mypy_cache/3.11/_ctypes.data.json
py_maker/.mypy_cache/3.11/_ctypes.meta.json
py_maker/.mypy_cache/3.11/_decimal.data.json
py_maker/.mypy_cache/3.11/_decimal.meta.json
py_maker/.mypy_cache/3.11/_operator.data.json
py_maker/.mypy_cache/3.11/_operator.meta.json
py_maker/.mypy_cache/3.11/_random.data.json
py_maker/.mypy_cache/3.11/_random.meta.json
py_maker/.mypy_cache/3.11/_socket.data.json
py_maker/.mypy_cache/3.11/_socket.meta.json
py_maker/.mypy_cache/3.11/_stat.data.json
py_maker/.mypy_cache/3.11/_stat.meta.json
py_maker/.mypy_cache/3.11/_thread.data.json
py_maker/.mypy_cache/3.11/_thread.meta.json
py_maker/.mypy_cache/3.11/_typeshed/__init__.data.json
py_maker/.mypy_cache/3.11/_typeshed/__init__.meta.json
py_maker/.mypy_cache/3.11/_warnings.data.json
py_maker/.mypy_cache/3.11/_warnings.meta.json
py_maker/.mypy_cache/3.11/_weakref.data.json
py_maker/.mypy_cache/3.11/_weakref.meta.json
py_maker/.mypy_cache/3.11/_weakrefset.data.json
py_maker/.mypy_cache/3.11/_weakrefset.meta.json
py_maker/.mypy_cache/3.11/abc.data.json
py_maker/.mypy_cache/3.11/abc.meta.json
py_maker/.mypy_cache/3.11/annotated_types/__init__.data.json
py_maker/.mypy_cache/3.11/annotated_types/__init__.meta.json
py_maker/.mypy_cache/3.11/argparse.data.json
py_maker/.mypy_cache/3.11/argparse.meta.json
py_maker/.mypy_cache/3.11/array.data.json
py_maker/.mypy_cache/3.11/array.meta.json
py_maker/.mypy_cache/3.11/ast.data.json
pyproject_maker-0.13.2.dist-info/WHEEL
pyproject_maker-0.13.2.dist-info/entry_points.txt
pyproject_maker-0.13.2.dist-info/METADATA
pyproject_maker-0.13.2.dist-info/RECORD
