Metadata-Version: 2.4
Name: pyproject-maker
Version: 0.13.2
Summary: A command line app to create a Python project skeleton.
Author: Grant Ramsay
Author-email: Grant Ramsay <seapagan@gmail.com>
License-Expression: MIT
Classifier: Development Status :: 4 - Beta
Classifier: Environment :: Console
Classifier: Intended Audience :: Developers
Classifier: License :: OSI Approved :: MIT License
Classifier: Operating System :: OS Independent
Classifier: Programming Language :: Python :: 3.9
Classifier: Programming Language :: Python :: 3.10
Classifier: Programming Language :: Python :: 3.11
Classifier: Programming Language :: Python :: 3.12
Classifier: Programming Language :: Python :: 3.13
Classifier: Topic :: Software Development
Classifier: Topic :: Software Development :: Code Generators
Classifier: Topic :: Utilities
Requires-Dist: gitpython>=3.1.43
Requires-Dist: jinja2>=3.1.4
Requires-Dist: pydantic>=2.9.2
Requires-Dist: pygithub>=2.4.0
Requires-Dist: requests>=2.32.3
Requires-Dist: rich>=13.9.2
Requires-Dist: rtoml>=0.12.0
Requires-Dist: simple-toml-settings>=0.8.0
Requires-Dist: typer>=0.12.5
Requires-Dist: validators>=0.34.0
Requires-Python: >=3.9
Project-URL: Bug Tracker, https://github.com/seapagan/py-maker/issues
Project-URL: Changelog, https://github.com/seapagan/py-maker/blob/main/CHANGELOG.md
Project-URL: Pull Requests, https://github.com/seapagan/py-maker/pulls
Project-URL: documentation, https://py-maker.seapagan.net
Project-URL: homepage, https://py-maker.seapagan.net
Project-URL: repository, https://github.com/seapagan/py-maker
